scrapy_extensions/__init__.py
scrapy_extensions/downloadermiddlewares.py
scrapy_extensions/extensions.py
scrapy_extensions/loggers.py
scrapy_extensions/middlewares.py
scrapy_extensions/pipelines.py
scrapy_extensions/py.typed
scrapy_extensions/utils.py
scrapy_extensions-1.1.0.dist-info/METADATA
scrapy_extensions-1.1.0.dist-info/WHEEL
scrapy_extensions-1.1.0.dist-info/licenses/LICENSE
scrapy_extensions-1.1.0.dist-info/RECORD
