Metadata-Version: 2.4
Name: scrapy-extensions
Version: 1.1.0
Summary: A collection of Scrapy extensions and other utilities
License: MIT
License-File: LICENSE
Author: Markus Shepherd
Author-email: markus@recommend.games
Requires-Python: >=3.10.0,<4.0
Classifier: Development Status :: 4 - Beta
Classifier: Intended Audience :: Developers
Classifier: License :: OSI Approved :: MIT License
Classifier: Operating System :: OS Independent
Classifier: Programming Language :: Python
Classifier: Programming Language :: Python :: 3
Classifier: Programming Language :: Python :: 3.10
Classifier: Programming Language :: Python :: 3.11
Classifier: Programming Language :: Python :: 3.12
Classifier: Programming Language :: Python :: 3.13
Classifier: Programming Language :: Python :: 3.14
Classifier: Topic :: Software Development :: Libraries :: Python Modules
Classifier: Typing :: Typed
Provides-Extra: blurhash
Requires-Dist: blurhash-numba[pillow] ; extra == "blurhash"
Requires-Dist: itemadapter
Requires-Dist: jmespath
Requires-Dist: numpy ; extra == "blurhash"
Requires-Dist: pillow (>=4.0.0) ; extra == "blurhash"
Requires-Dist: scrapy (>=2.0.0,<3.0.0)
Requires-Dist: twisted
Requires-Dist: w3lib (>=2.0.0,<3.0)
Project-URL: Documentation, https://MarkusShepherd.github.io/scrapy-extensions
Project-URL: Homepage, https://MarkusShepherd.github.io/scrapy-extensions
Project-URL: Repository, https://github.com/MarkusShepherd/scrapy-extensions
